rfdist/RF.py
rfdist/RF_NTT.py
rfdist/__init__.py
rfdist/ntt.py
rfdist-0.9.dist-info/LICENSE
rfdist-0.9.dist-info/METADATA
rfdist-0.9.dist-info/WHEEL
rfdist-0.9.dist-info/top_level.txt
rfdist-0.9.dist-info/RECORD
